[{"id":1,"name":"Alice Johnson","age":28,"city":"america"},{"id":2,"name":"Bob Smith","age":34,"city":"Los Angeles"},{"id":3,"name":"Charlie Davis","age":22,"city":"Chicago"},{"id":4,"name":"Dana Lee","age":30,"city":"Houston"},{"id":5,"name":"Evan Brown","age":45,"city":"Phoenix"},{"id":6,"name":"Fiona Clark","age":29,"city":"Philadelphia"},{"id":7,"name":"George Miller","age":37,"city":"San Antonio"},{"id":8,"name":"Hannah Wilson","age":26,"city":"San Diego"},{"id":9,"name":"Ian Martinez","age":31,"city":"Dallas"},{"id":10,"name":"Jessica Taylor","age":33,"city":"San Jose"},{"id":11,"name":"Kyle White","age":40,"city":"Austin"},{"id":12,"name":"Laura Harris","age":27,"city":"Jacksonville"},{"id":13,"name":"Mike Thomas","age":36,"city":"Fort Worth"},{"id":14,"name":"deva","age":32,"city":"chennai"},{"id":15,"name":"Oliver Walker","age":41,"city":"Charlotte"}]